{
  "id": "Bugs2FIX-20260502002627-a0168493",
  "bugHistory": [],
  "completedAt": null,
  "outlineVersion": "v0",
  "executionMethod": "",
  "tags": [],
  "description": "Fix for bug Bug-20260502002524-e5174874: Parse error in Invoke-ConventionComplianceSuite.Tests.ps1 line 183: The '<' operator is reserved for future use.",
  "lastSeenAt": "2026-05-01T16:26:27.513709Z",
  "linkedFeatures": [],
  "fixesImplementedCount": 0,
  "title": "FIX: The '<' operator is reserved for future use.",
  "parentId": "Bug-20260502002524-e5174874",
  "type": "Bugs2FIX",
  "result": null,
  "filesFixedCount": 0,
  "executedAt": null,
  "outlineTag": "OUTLINE-PROTO-v0",
  "firstSeenAt": "2026-05-01T16:26:27.513709Z",
  "priority": "HIGH",
  "suggestedBy": "CronAiAthon",
  "outlinePhase": "assessment",
  "affectedFiles": [
    "C:\\PowerShellGUI\\tests\\Invoke-ConventionComplianceSuite.Tests.ps1"
  ],
  "plannedAt": null,
  "linkedBugs": [],
  "status": "DONE",
  "sinId": "",
  "bugReferrals": [
    "Bug-20260502002524-e5174874"
  ],
  "implementedAt": null,
  "notes": "Auto-reconciled: target file currently parses cleanly (or absent). Path=C:\\PowerShellGUI\\tests\\Invoke-ConventionComplianceSuite.Tests.ps1",
  "category": "parsing",
  "reopenedAt": null,
  "created": "2026-05-01T16:26:27.513709Z",
  "bugResurfaced": false,
  "source": "BugTracker",
  "sessionModCount": 1,
  "executionAgent": "",
  "modified": "2026-05-01T16:26:27.513709Z",
  "filesRemainingCount": 0,
  "countermeasures": [],
  "acknowledged": null,
  "resolved_by": "BacklogReconcile-AutoParse",
  "resolved_at": "2026-05-04T23:35:56.078841+08:00",
  "archiveMetadata": {
    "archivedAt": "2026-05-16T00:04:48",
    "archiveFolder": "~Archive",
    "archiveReason": "FIXED - all required fix implementations resolved",
    "hindsightNote": "TODO: Document retrospective approach - what would you do differently if starting again?",
    "fixImplementations": "TODO: List every fix step that was required to fully resolve this bug item"
  }
}