{
  "id": "Bug-20260504150839-aaf8071d",
  "bugHistory": [],
  "completedAt": null,
  "outlineVersion": "v0",
  "executionMethod": "",
  "tags": [],
  "description": "Parse error in PwSh-HelpFilesUpdateSource-ReR.psm1 line 422: Unexpected token '“' in expression or statement.",
  "lastSeenAt": "2026-05-04T07:08:39.9353793Z",
  "linkedFeatures": [],
  "fixesImplementedCount": 0,
  "title": "Unexpected token '“' in expression or statement.",
  "parentId": "",
  "type": "Bug",
  "result": null,
  "filesFixedCount": 0,
  "executedAt": null,
  "outlineTag": "OUTLINE-PROTO-v0",
  "firstSeenAt": "2026-05-04T07:08:39.9353793Z",
  "priority": "HIGH",
  "suggestedBy": "CronAiAthon-BugTracker",
  "outlinePhase": "assessment",
  "affectedFiles": [
    "C:\\PowerShellGUI\\~REPORTS\\remediation-backups\\20260404-211451\\PwSh-HelpFilesUpdateSource-ReR.psm1"
  ],
  "plannedAt": null,
  "linkedBugs": [],
  "status": "DONE",
  "sinId": "SIN-20260504150841-23a9d59d",
  "bugReferrals": [],
  "implementedAt": null,
  "notes": "New sin created: SIN-20260504150841-23a9d59d\nAuto-reconciled: target file currently parses cleanly (or absent). Path=C:\\PowerShellGUI\\modules\\PwSh-HelpFilesUpdateSource-ReR.psm1",
  "category": "parsing",
  "reopenedAt": null,
  "created": "2026-05-04T07:08:39.934371Z",
  "bugResurfaced": false,
  "source": "BugTracker",
  "sessionModCount": 1,
  "executionAgent": "",
  "modified": "2026-05-04T07:08:39.9353793Z",
  "filesRemainingCount": 0,
  "countermeasures": [],
  "acknowledged": null,
  "resolved_by": "BacklogReconcile-AutoParse",
  "resolved_at": "2026-05-04T23:35:44.8957101+08:00"
}