{
  "executionMethod": "",
  "type": "Bugs2FIX",
  "filesFixedCount": 0,
  "linkedBugs": [],
  "sinId": "",
  "completedAt": null,
  "outlineTag": "OUTLINE-PROTO-v0",
  "modified": "2026-05-15T16:28:09.7860953Z",
  "fixesImplementedCount": 0,
  "sessionModCount": 1,
  "executionAgent": "CronAiAthon-Pipeline",
  "priority": "CRITICAL",
  "lastSeenAt": "2026-05-15T16:19:05.3803751Z",
  "result": null,
  "created": "2026-05-15T16:19:05.3802566Z",
  "source": "BugTracker",
  "status": "IN-PROGRESS",
  "bugReferrals": [
    "Bug-20260516001722-290c0f8d"
  ],
  "implementedAt": null,
  "reopenedAt": null,
  "title": "FIX: [2026-05-11 00:08:51][BOOT][ERROR] FATAL: HttpListener failed to start on port 8042 — Exception calling \"Start\" with \"0\" argument(s): \"Failed to listen on prefix 'http://127.0.0.1:8042/' because it co",
  "id": "Bugs2FIX-20260516001905-66f8b07d",
  "affectedFiles": [
    "C:\\PowerShellGUI\\logs\\engine-bootstrap.log"
  ],
  "countermeasures": [],
  "firstSeenAt": "2026-05-15T16:19:05.3803349Z",
  "filesRemainingCount": 0,
  "linkedFeatures": [],
  "acknowledged": null,
  "category": "crash-log",
  "parentId": "Bug-20260516001722-290c0f8d",
  "tags": [],
  "executedAt": null,
  "outlineVersion": "v0",
  "suggestedBy": "CronAiAthon",
  "description": "Fix for bug Bug-20260516001722-290c0f8d: Error pattern in log engine-bootstrap.log:176",
  "outlinePhase": "assessment",
  "plannedAt": "2026-05-15T16:28:09.7860953Z",
  "bugHistory": [],
  "bugResurfaced": false,
  "notes": "Auto-transitioned to IN-PROGRESS by Drain-Bugs2FIX-Pass2 at 2026-05-15T16:28:09.7860953Z"
}
