{
  "version": "2604.B1.V32.0",
  "phases": {
    "dns_resolution": {
      "error": "",
      "completedAt": "2026-04-18T14:55:17.7593103+08:00",
      "status": "ok",
      "durationMs": 39931,
      "count": 71
    },
    "modules": {
      "error": "",
      "completedAt": "2026-04-18T14:54:50.6600193+08:00",
      "status": "ok",
      "durationMs": 12832,
      "count": 108
    },
    "folders": {
      "error": "",
      "completedAt": "2026-04-18T14:54:41.7966392+08:00",
      "status": "ok",
      "durationMs": 3969,
      "count": 356
    },
    "urls_ips": {
      "error": "",
      "completedAt": "2026-04-18T14:54:50.6754523+08:00",
      "status": "ok",
      "durationMs": 12847,
      "count": 2133
    },
    "configs": {
      "error": "",
      "completedAt": "2026-04-18T14:54:55.8785753+08:00",
      "status": "ok",
      "durationMs": 18051,
      "count": 51
    },
    "scripts": {
      "error": "",
      "completedAt": "2026-04-18T14:54:50.6672715+08:00",
      "status": "ok",
      "durationMs": 12839,
      "count": 2293
    }
  },
  "lastFullScan": ""
}
